bsmutility/__init__.py
bsmutility/auipathbar.py
bsmutility/autocomplete.py
bsmutility/bsminterface.py
bsmutility/bsmxpm.py
bsmutility/configfile.py
bsmutility/convert.py
bsmutility/debugger.py
bsmutility/debugtool.py
bsmutility/dirtreectrl.py
bsmutility/editor.py
bsmutility/editor_base.py
bsmutility/fileviewbase.py
bsmutility/findlistctrl.py
bsmutility/findmixin.py
bsmutility/frameplus.py
bsmutility/misctools.py
bsmutility/pymgr_helpers.py
bsmutility/pysurface.py
bsmutility/quaternion.py
bsmutility/richdialog.py
bsmutility/shell.py
bsmutility/shell_base.py
bsmutility/signalselsettingdlg.py
bsmutility/surface.py
bsmutility/utility.py
bsmutility/version.py
bsmutility-0.4.0.dist-info/licenses/LICENSE
bsmutility-0.4.0.dist-info/METADATA
bsmutility-0.4.0.dist-info/WHEEL
bsmutility-0.4.0.dist-info/top_level.txt
bsmutility-0.4.0.dist-info/RECORD
