Metadata-Version: 2.4
Name: bsmutility
Version: 0.4.0
Summary: Some helper class
Author-email: Tianzhu Qiao <tq@feiyilin.com>
License: MIT License
Project-URL: Homepage, https://github.com/tianzhuqiao/bsmutility
Classifier: Operating System :: OS Independent
Requires-Python: >=3.0
License-File: LICENSE
Requires-Dist: wxpython>=4.2.1
Requires-Dist: matplotlib>=3.8.1
Requires-Dist: numpy
Requires-Dist: click
Requires-Dist: pandas
Requires-Dist: propgrid>=0.1.6
Requires-Dist: mplpanel>=0.2.4
Requires-Dist: aui2>=0.2.0
Requires-Dist: pyshortcuts
Requires-Dist: glsurface>=0.1.2
Dynamic: license-file
